txspinneret/__init__.py
txspinneret/_version.py
txspinneret/interfaces.py
txspinneret/query.py
txspinneret/resource.py
txspinneret/route.py
txspinneret/util.py
txspinneret/test/__init__.py
txspinneret/test/test_query.py
txspinneret/test/test_resource.py
txspinneret/test/test_route.py
txspinneret/test/test_util.py
txspinneret/test/util.py
txspinneret-0.1.3.dist-info/DESCRIPTION.rst
txspinneret-0.1.3.dist-info/METADATA
txspinneret-0.1.3.dist-info/metadata.json
txspinneret-0.1.3.dist-info/RECORD
txspinneret-0.1.3.dist-info/top_level.txt
txspinneret-0.1.3.dist-info/WHEEL
