Metadata-Version: 2.0
Name: txspinneret
Version: 0.1.3
Summary: Spinneret is a collection of higher-level utility classes and functions for Twisted Web.
Home-page: https://github.com/jonathanj/txspinneret
Author: Jonathan Jacobs
Author-email: UNKNOWN
License: MIT
Keywords: twisted web routing
Platform: UNKNOWN
Classifier: Development Status :: 4 - Beta
Classifier: Intended Audience :: Developers
Classifier: License :: OSI Approved :: MIT License
Classifier: Operating System :: MacOS :: MacOS X
Classifier: Operating System :: Microsoft :: Windows
Classifier: Operating System :: POSIX
Classifier: Programming Language :: Python :: 2
Classifier: Programming Language :: Python :: 2.7
Classifier: Programming Language :: Python :: Implementation :: CPython
Classifier: Programming Language :: Python :: Implementation :: PyPy
Classifier: Topic :: Software Development :: Libraries :: Python Modules
Requires-Dist: zope.interface (>=3.6.0)
Requires-Dist: twisted (>=13.2.0)
Provides-Extra: doc
Requires-Dist: Sphinx (==1.2); extra == 'doc'
Requires-Dist: sphinx-rtd-theme (==0.1.6); extra == 'doc'
Requires-Dist: sphinxcontrib-zopeext; extra == 'doc'
Provides-Extra: dev
Requires-Dist: testtools (==0.9.35); extra == 'dev'
